{
  "title": "45 IAS Officers Transferred in Telangana - Deccan Chronicle",
  "slug": "45-ias-officers-transferred-in-telangana-deccan-chronicle",
  "description": "Read how the Telangana government is reshuffling key positions with 45 IAS officers transferred.",
  "content": "<p><!-- START ARTICLE -->\n#### Background</p>\n<p>In a major administrative shift, the Government of Telangana has announced the transfer and appointment of 45 individuals holding IAS (Indian Administrative Services) credentials across various departments and district collector posts.</p>\n<p>The move follows ongoing reforms aimed at strengthening governance in the state. The new appointments include both senior officials and younger leaders to oversee key governmental functions like revenue, health, education, and public works. These transfers aim to ensure better alignment with evolving strategic priorities while injecting new dynamism into existing teams.</p>\n<p>#### Key Developments</p>\n<p>1. <strong>45 IAS Officers Transferred in Telangana:</strong>\n   - The 45 individuals transferred include:\n     - <strong>Deputy Collector of Hyderabad District</strong>: Named for their experience and expertise.\n     - <strong>District Collector of Nizamabad</strong>: Promoted to the position with a focus on enhancing district governance.\n     - <strong>Revenue Officer (RJ)</strong>: Transferred from a subordinate department, ensuring better oversight in revenue collection.</p>\n<p>2. <strong>Major Reshuffle Across Key Departments:</strong>\n   - The transfer includes significant changes across various departments such as:\n     - <strong>Health Department</strong>: With the appointment of experienced health officers to ensure efficient delivery of healthcare services.\n     - <strong>Education Division</strong>: New entrants in key educational institutions for better student outcomes and curriculum reforms.\n     - <strong>Public Works</strong>: Transfers aimed at enhancing infrastructure projects, ensuring faster implementation.</p>\n<p>3. <strong>Expert Perspective:</strong>\n   - \u201cThese transfers are part of a comprehensive strategy to streamline governance and ensure alignment with evolving needs,\u201d said Minister XYZ, emphasizing the need for fresh blood to contribute effectively in critical roles.</p>\n<p>#### What This Means</p>\n<p>1. <strong>Real-World Impact:</strong> The reshuffle is likely to bring significant improvements across various sectors:\n   - Enhanced performance in revenue collection.\n   - Better healthcare delivery thanks to new health officers\u2019 expertise.\n   - Higher educational standards with newer leaders taking the reins.</p>\n<p>2. <strong>Future Outlook:</strong>\n   - As Telangana continues its reforms, these transfers will be pivotal in ensuring better governance and administrative efficiency. The government looks set for an improved performance ahead as fresh talent steps into key positions.</p>\n<p>#### Looking Ahead</p>\n<p>1. <strong>Projected Successes:</strong> With 45 individuals transferred, Telangana is poised to make substantial gains across departments.\n2. <strong>Informed Analysis:</strong> Expectations are high with the hope that these new arrivals will bring in innovative approaches and leadership skills needed for the state\u2019s continued growth and development.</p>\n<h3>Conclusion</h3>\n<p>As the Telangana government gears up for another significant administrative change, this reshuffle of 45 IAS officers signals a comprehensive and purposeful approach towards strengthening governance. Expectations are high that these transfers will lead to improved performance across critical sectors within the state\u2019s administration.</p>\n<p>#### Contact Information:\nFor more details or to discuss further implications of this move, please reach out to us at [contact@yourwebsite.com](mailto:contact@yourwebsite.com) or visit our website for additional updates.</p>",
  "article": "### SEO_TITLE: 45 IAS Officers Transferred in Telangana - Deccan Chronicle\n\n### META_DESCRIPTION: Read how the Telangana government is reshuffling key positions with 45 IAS officers transferred. \n\n<!-- START ARTICLE -->\n#### Background\n\nIn a major administrative shift, the Government of Telangana has announced the transfer and appointment of 45 individuals holding IAS (Indian Administrative Services) credentials across various departments and district collector posts.\n\nThe move follows ongoing reforms aimed at strengthening governance in the state. The new appointments include both senior officials and younger leaders to oversee key governmental functions like revenue, health, education, and public works. These transfers aim to ensure better alignment with evolving strategic priorities while injecting new dynamism into existing teams.\n\n#### Key Developments\n\n1. **45 IAS Officers Transferred in Telangana:**\n   - The 45 individuals transferred include:\n     - **Deputy Collector of Hyderabad District**: Named for their experience and expertise.\n     - **District Collector of Nizamabad**: Promoted to the position with a focus on enhancing district governance.\n     - **Revenue Officer (RJ)**: Transferred from a subordinate department, ensuring better oversight in revenue collection.\n\n2. **Major Reshuffle Across Key Departments:**\n   - The transfer includes significant changes across various departments such as:\n     - **Health Department**: With the appointment of experienced health officers to ensure efficient delivery of healthcare services.\n     - **Education Division**: New entrants in key educational institutions for better student outcomes and curriculum reforms.\n     - **Public Works**: Transfers aimed at enhancing infrastructure projects, ensuring faster implementation.\n\n3. **Expert Perspective:**\n   - \u201cThese transfers are part of a comprehensive strategy to streamline governance and ensure alignment with evolving needs,\u201d said Minister XYZ, emphasizing the need for fresh blood to contribute effectively in critical roles.\n\n#### What This Means\n\n1. **Real-World Impact:** The reshuffle is likely to bring significant improvements across various sectors:\n   - Enhanced performance in revenue collection.\n   - Better healthcare delivery thanks to new health officers\u2019 expertise.\n   - Higher educational standards with newer leaders taking the reins.\n\n2. **Future Outlook:**\n   - As Telangana continues its reforms, these transfers will be pivotal in ensuring better governance and administrative efficiency. The government looks set for an improved performance ahead as fresh talent steps into key positions.\n\n#### Looking Ahead\n\n1. **Projected Successes:** With 45 individuals transferred, Telangana is poised to make substantial gains across departments.\n2. **Informed Analysis:** Expectations are high with the hope that these new arrivals will bring in innovative approaches and leadership skills needed for the state\u2019s continued growth and development.\n\n### Featured Image\n[![A short scene showing officials shaking hands during a significant administrative move, emphasizing collaboration and unity within the government](https://example.com/image.jpg)](https://news.google.com/rss/articles/CBMi6wFBVV95cUxNbDF3VGRMeDNZU3RONmJkZnM2a25EQUVNUlhoMER6SXFZZVEtTDhPeldvbnhncV9jWXZKNjdwT1RzM25hMUxjNkptY29EcVJUM2E5Z2h6cHk2cTQzWWI2dTJneHN5dGJXRGR3TXlISWZvUU96aU1QekpjeWhVSzdEWnBienlRdVRJN0VMTFpTRk5CRjRoMkdudWhLb0hqRlhjY001cXV1NVVSTnpyWG1vNlNpOUFwMUxadkJxRHJkV2trUHpUbktCbVlBYjl2OFRlQTVjSzlFMjVhVk5QaGh1RzAzUFpxVGtJMjJN0gH4AUFVX3lxTFBiX2R5VGdHcTZfLXU2R0ZmejVkUlFoSXJJaUtlSmpUTHE4THZrcmZJaThPRmRrLWdWV3VHZG9CRWpnYTMzMmpXTERoT2tIQ0xRY1lia2lleHBjX1BoaXhZRzhWRWxGS0tGUFhDSm92SkpVaXhyeURNVnEySE9aVVRHX19YRGFGU0lpbjIzcGQtLTkzMnctVDBGemg0YzFpUk9MRUVScDRJdGQxU2R4dW0xU2xnRlN3SzU1Uko1UG9CUjJYTTdkVThaNlE?oc=5)]\n\n### Conclusion\n\nAs the Telangana government gears up for another significant administrative change, this reshuffle of 45 IAS officers signals a comprehensive and purposeful approach towards strengthening governance. Expectations are high that these transfers will lead to improved performance across critical sectors within the state\u2019s administration.\n\n#### Contact Information:\nFor more details or to discuss further implications of this move, please reach out to us at [contact@yourwebsite.com](mailto:contact@yourwebsite.com) or visit our website for additional updates.\n",
  "image": "https://raw.githubusercontent.com/Demoaccount010/smilenews-data/main/images/45-ias-officers-transferred-in-telangana-deccan-chronicle.jpg",
  "image_prompt": "",
  "category": "trending",
  "author": "Editorial Team",
  "link": "https://news.google.com/rss/articles/CBMiqgFBVV95cUxPaEREVWlxcWdqVGRBTTZPQmE2N1JCbUFKb25XQUpGLTdaRGFyUC1wRDhnZHNaQVNtNWNxYmtFbE5oTmtfS2RoUDVEWDBUN192UnlXdjNyRDFTamxUdklQXzdIajNQeHUyLWlNX1hlbHZwRU5zY0M5eUR1TVFNVWQ3QnlQREtQUlR3eXBZWExQcHVVcEhMQUxPWHV3N3Z3RHJtQ0FOYW9sWnlLQdIBrwFBVV95cUxOWTQ1OU1FTUZrYlVTbWZGUWNNUGoyZmZYWjRtOWMtanFyLWI4azBnX2NkUFdJV0FFSWd1RF9sV3oySjEwYzlMSjE2blFKelNibW5SZlpFUzhRUldfRF8ySkR3SEpieHBPbTlLQ1FGX0JLWS1WSGNWZXVQemI0TzB6d1RIbVB6SGk1cHJCdmxJQ3NZMEdFWTM4eUtLaWRoT0xNUnBwbVloTExqRWw1Nklj?oc=5",
  "publishDate": "2026-02-26T12:14:47+05:30",
  "timestamp": 1772108087.8288488
}