{
  "title": "England\u2019s Pollyfilla Returns to Glory with Jacks of All Trades",
  "slug": "england-s-pollyfilla-returns-to-glory-with-jacks-of-all-trades",
  "description": "Learn how Jacks of all trades provides England's priceless Pollyfilla once more, and discover the impact it has on the cricketing world. Stay updated with exper",
  "image": "https://raw.githubusercontent.com/Demoaccount010/smilenews-data/main/images/england-s-pollyfilla-returns-to-glory-with-jacks-of-all-trades.jpg",
  "category": "trending",
  "publishDate": "2026-02-28T00:41:34+05:30",
  "timestamp": 1772239294.8802488,
  "author": "Editorial Team"
}