{
  "title": "From March 1 into Dandakaranya for 40 Years, Devuji's Arc Mirrors Maoism Rise and Fall - ThePrint",
  "slug": "from-march-1-into-dandakaranya-for-40-years-devuji-s-arc-mirrors-maoism-rise-and",
  "description": "A comprehensive look at the legendary figure of Devuji\u2019s journey through history, tracing his arc from a Maoist leader to the top official in Telangana\u2019s police",
  "image": "https://raw.githubusercontent.com/Demoaccount010/smilenews-data/main/images/from-march-1-into-dandakaranya-for-40-years-devuji-s-arc-mirrors-maoism-rise-and.jpg",
  "category": "trending",
  "publishDate": "2026-02-26T04:04:39+05:30",
  "timestamp": 1772078679.0252185,
  "author": "Editorial Team"
}