{
  "title": "India Has Not Condemned Khamenei\u2019s Death, Why and What It Means",
  "slug": "india-has-not-condemned-khamenei-s-death-why-and-what-it-means",
  "description": "Why has India not condemned Iran's former Supreme Leader Ayatollah Ali Khamenei\u2019s death? The reasons behind this stance are explored along with the potential co",
  "content": "<p>The recent death of Iran's former Supreme Leader, Ayatollah Ali Khamenei, has raised questions about India's stance in a geopolitical landscape dominated by regional powers like Iran and Israel. While India maintains an isolationist foreign policy characterized by its focus on balancing relationships within the Indian Ocean region, this incident provides a stark contrast.</p>\n<p>India\u2019s position is noteworthy because it reflects deeper considerations of broader strategic interests rather than immediate nationalistic reactions. The decision to remain neutral suggests a preference for maintaining strategic autonomy in international affairs. This approach underscores how foreign policies are shaped by complex regional dynamics and changing global power structures.</p>\n<p>In the wake of Khamenei's death, India\u2019s cautious response has implications not only for its domestic politics but also for global geopolitical trends. The assassination of an influential Iranian figure could signal shifts in Iran\u2019s role within the region, potentially weakening Iran\u2019s position as a regional ally. This event highlights how countries must navigate delicate negotiations and avoid political rapprochements that could lead to diplomatic crises.</p>\n<p>Experts have noted that India's decision reflects a deeper understanding of regional dynamics and strategic priorities. While other nations like Israel have condemned Khamenei immediately after receiving conflicting reports, India has chosen to remain silent. This approach underscores the need for countries to maintain their position as non-aligned players in an increasingly complex global landscape.</p>\n<p>Analysts predict continued regional instability and renewed scrutiny of Iran\u2019s nuclear program. The assassination has highlighted the complexities of international politics and underscored the importance of maintaining strategic autonomy without falling into political extremes. India\u2019s decision is seen as a reflection of its evolving approach to geopolitics, reflecting changing global dynamics.</p>\n<p>In conclusion, while Khamenei's death may have raised eyebrows for some, it underscores the need for countries to maintain their position as independent players in an increasingly interconnected world. This incident serves as a reminder that foreign policy decisions are shaped by complex regional and international factors rather than immediate nationalistic reactions.</p>",
  "article": "### SEO_TITLE: India Has Not Condemned Khamenei\u2019s Death, Why and What It Means\n\n#### META_DESCRIPTION:\nWhy has India not condemned Iran's former Supreme Leader Ayatollah Ali Khamenei\u2019s death? The reasons behind this stance are explored along with the potential consequences for regional dynamics.\n\n---\n\n### KEY DEVELOPMENTS:\n\nThe recent passing of Iran's former Supreme Leader, Ayatollah Ali Khamenei, in his 86th year has led to a mix of speculation and debate among global observers. India, traditionally known for maintaining a neutral stance on geopolitical issues involving its neighbors, has shown no signs of condemning the death of this influential figure. This unusual response sparks interest not only within India but also internationally.\n\n#### INDIA\u2019S POSITION:\n\nIndia\u2019s position is noteworthy because it often maintains an isolationist approach in foreign policy. This case illustrates why India's response might be perceived as a deviation from its usual stance. The reasons for India's hesitation include the need to balance relations with both Iran and the United States, where Khamenei played a significant role.\n\nThe Indian government has taken a cautious approach, likely due to concerns about destabilizing regional alliances or engaging in political rapprochement that could lead to diplomatic fallout. This reluctance contrasts sharply with other countries, such as Israel, which have condemned the death of Khamenei immediately after receiving conflicting information regarding his cause of death.\n\n#### INDUSTRY IMPACT:\n\nThe assassination of a high-ranking Iranian figure has implications for the broader Middle East geopolitical landscape. The role of Iran in regional politics has been instrumental since its inception following the 1979 revolution, and losing such a prominent leader could signal a shift in power dynamics that may be harder to reverse.\n\nKhamenei was known for his uncompromising stance on issues like nuclear proliferation, missile development, and political influence. His death could potentially weaken Iran\u2019s position as an ally for countries seeking stability and security within the region.\n\n#### EXPERT PERSPECTIVE:\n\nExperts have noted that India's decision reflects a deeper understanding of regional dynamics and is influenced by the need to maintain its strategic autonomy in the face of international pressures. This approach underscores how foreign policy decisions are often shaped by a country\u2019s broader geopolitical interests, rather than immediate nationalistic responses.\n\nAnalysts argue that while India has remained neutral on this issue, it may have been aware of conflicting reports about Khamenei's cause of death and feared a potential diplomatic incident or escalation of tensions. The silence from India suggests they prefer to maintain their position as a non-aligned country in the international arena.\n\n#### REAL-WORLD IMPACT:\n\nIndia\u2019s cautious approach is crucial for maintaining its reputation as an independent global player. By not condemning Khamenei's death, India sends a message that it prioritizes its relationships over immediate nationalistic reactions, which could have implications for how other nations view Indian foreign policy in the future.\n\n#### LOOKING AHEAD:\n\nAs the dust settles on this event, experts predict continued regional instability and renewed scrutiny of Iran\u2019s nuclear program. The assassination has highlighted the complexities of international politics and the need for countries to navigate these issues without falling into political extremes. India\u2019s decision is seen as a reflection of its evolving approach towards geopolitics, reflecting changing global dynamics.\n\n---\n\n### FEATURED_IMAGE_PROMPT:\nA dramatic scene in front of a podium at an international conference hall, with figures from various nations discussing current events amidst the backdrop of historical documents and maps symbolizing regional power balances. The photograph captures a moment of intense diplomatic discourse as participants make final decisions that could shift the trajectory of global politics.\n\n### CONTENT_HTML:\n\nThe recent death of Iran's former Supreme Leader, Ayatollah Ali Khamenei, has raised questions about India's stance in a geopolitical landscape dominated by regional powers like Iran and Israel. While India maintains an isolationist foreign policy characterized by its focus on balancing relationships within the Indian Ocean region, this incident provides a stark contrast.\n\nIndia\u2019s position is noteworthy because it reflects deeper considerations of broader strategic interests rather than immediate nationalistic reactions. The decision to remain neutral suggests a preference for maintaining strategic autonomy in international affairs. This approach underscores how foreign policies are shaped by complex regional dynamics and changing global power structures.\n\nIn the wake of Khamenei's death, India\u2019s cautious response has implications not only for its domestic politics but also for global geopolitical trends. The assassination of an influential Iranian figure could signal shifts in Iran\u2019s role within the region, potentially weakening Iran\u2019s position as a regional ally. This event highlights how countries must navigate delicate negotiations and avoid political rapprochements that could lead to diplomatic crises.\n\nExperts have noted that India's decision reflects a deeper understanding of regional dynamics and strategic priorities. While other nations like Israel have condemned Khamenei immediately after receiving conflicting reports, India has chosen to remain silent. This approach underscores the need for countries to maintain their position as non-aligned players in an increasingly complex global landscape.\n\nAnalysts predict continued regional instability and renewed scrutiny of Iran\u2019s nuclear program. The assassination has highlighted the complexities of international politics and underscored the importance of maintaining strategic autonomy without falling into political extremes. India\u2019s decision is seen as a reflection of its evolving approach to geopolitics, reflecting changing global dynamics.\n\nIn conclusion, while Khamenei's death may have raised eyebrows for some, it underscores the need for countries to maintain their position as independent players in an increasingly interconnected world. This incident serves as a reminder that foreign policy decisions are shaped by complex regional and international factors rather than immediate nationalistic reactions.",
  "image": "https://raw.githubusercontent.com/Demoaccount010/smilenews-data/main/images/india-has-not-condemned-khamenei-s-death-why-and-what-it-means.jpg",
  "image_prompt": "A dramatic scene in front of a podium at an international conference hall, with figures from various nations discussing current events amidst the backdrop of historical documents and maps symbolizing regional power balances. The photograph captures a moment of intense diplomatic discourse as participants make final decisions that could shift the trajectory of global politics.",
  "category": "trending",
  "author": "Editorial Team",
  "link": "https://news.google.com/rss/articles/CBMitAFBVV95cUxQaURhdmNxdWNuZzRuaTNHdU9BQjJIcmlLSndiS2N2dXlIeFdvTXRUMnk1UmxhUEwzZUJBZkpfLWZxMktWQWplLWl2UFFmWk5xWVo3Ylh3aWt1end0QThYcTRPd3BiR1pPZ0NuMW4zU2VVSm1jaDhfVnNYc3FoUC1PS3pwdVhlRTgtNFlOOXJfUElOZjdrN2FqbnV2M3VYTGg4bnE4RExqZ3ZUdUdZT1k2RkdVSEg?oc=5",
  "publishDate": "2026-03-04T02:22:58+05:30",
  "timestamp": 1772590978.9008722
}