{
  "title": "Yunus Out, India To Restore All Visa Services in Bangladesh Soon",
  "slug": "yunus-out-india-to-restore-all-visa-services-in-bangladesh-soon",
  "description": "India is poised to fully restore all visa services in Bangladesh following the resignation of Yunus. This move aims to ease travel restrictions and boost econom",
  "image": "https://raw.githubusercontent.com/Demoaccount010/smilenews-data/main/images/yunus-out-india-to-restore-all-visa-services-in-bangladesh-soon.jpg",
  "category": "trending",
  "publishDate": "2026-02-21T01:28:49+05:30",
  "timestamp": 1771637329.868734,
  "author": "Editorial Team"
}